<?xml version="1.0" encoding="ISO-8859-9" standalone="yes"?>
<root>
<name>== (eþittir)</name>

<category>Kontrol</category>

<subcategory>Ýliþkisel Operatörler</subcategory>

<usage>Web &amp; Uygulama</usage>

<example>
<image></image>
<code>
int a = 23;
int b = 23;
if(a == b) {
  println("variables a and b are equal");
}
</code>
</example>

<description>
Ýki deðerin eþit olup olmadýðýna karar verir. Eþitlik operatörü atama operatöründen farklýdýr.
</description>

<syntax>
<c>deðer1</c> == <c>deðer2</c>
</syntax>

<parameter>
<label>deðer1</label>
<description>int, float, char, byte, boolean, String</description>
</parameter>

<parameter>
<label>value2</label>
<description>int, float, char, byte, boolean, String</description>
</parameter>

<returns></returns>

<related>
&gt; (greater than)
&lt; (less than)
&gt;= (greater than or equal to)
&lt;= (less than or equal to)
!= (inequality)
</related>

<availability>1.0</availability>

<type>Operator</type>

<partof>PDE</partof>








</root>