<?xml version="1.0" encoding="ISO-8859-9" standalone="yes"?>
<root>
<name>setup()</name>

<category>Yapý</category>

<subcategory></subcategory>

<usage>Web &amp; Uygulama</usage>

<example>
<image></image>
<code>
void setup() {
  size(200, 200);
  background(0);
  noStroke();
  fill(102);
}

int a = 0;

void loop() {
  rect(a++%width, 10, 2, 80); 
}
</code>
</example>

<description>
Program çalýþmaya baþladýðý zaman bir defa çaðrýlan fonksiyon. <b>loop()</b> baþlamadan önce ekran boyutu, arkaplan rengi, resim yükleme gibi baþlangýç ortam özelliklerini tanýmlamak için kullanýlýr. <b>setup()</b> içinde belirlenen deðiþkenlere <b>loop()</b> içinden eriþilemez.
</description>

<syntax>
void setup() {
  <c>anlatýmlar</c>
}
</syntax>

<parameter>
<label>anlatýmlar</label>
<description>herhangi bir geçerli anlatým</description>
</parameter>

<returns>Yok</returns>

<related>
loop()
size()
</related>

<availability>1.0</availability>

<type>Function</type>

<partof>PDE</partof>








</root>