<?xml version="1.0" encoding="UTF-8" standalone="yes"?>
<root>
<name>link()</name>

<category>Input</category>

<subcategory>Web</subcategory>

<usage>Web &amp; Application</usage>

<example>
<image></image>
<code>
void draw() { 
  rect(20, 20, 60, 60); 
} 
 
void mousePressed() { 
  link("http://processing.org"); 
} 
</code>
</example>

<example>
<image></image>
<code>
void draw() { 
  rect(20, 20, 60, 60); 
} 
 
void mousePressed() { 
  link("http://processing.org", "_new"); 
}
 
</code>
</example>

<description>
Links to a webpage either in the same window or in a new window. The complete URL must be specified.
</description>

<syntax>
link(<c>url</c>)
link(<c>url</c>, <c>target</c>)
</syntax>

<parameter>
<label>url</label>
<description>String: complete url as a String in quotes</description>
</parameter>

<parameter>
<label>target</label>
<description>String: name of the window to load the URL as a string in quotes</description>
</parameter>

<returns>None</returns>

<related></related>

<availability>1.0</availability>

<type>function</type>

<partof>Core</partof>

<level>Extended</level>

</root>
