<?xml version="1.0" encoding="UTF-8" standalone="yes"?>
<root>
<name>noLoop()</name>

<category>Structure</category>

<subcategory></subcategory>

<usage>Web &amp; Application</usage>

<example>
<image></image>
<applet></applet>
<code>
void setup() {
  size(200, 200);
  noLoop();
}

void draw() {
  line(10, 10, 190, 190);
}
</code>
</example>

<example>
<image></image>
<applet></applet>
<code>
void setup() {
  size(200, 200);
}

float x = 0.0;

void draw() {
  background(204);
  x = x + 0.1;
  if (x &gt; width) {
    x = 0;
  }
  line(x, 0, x, height); 
}

void mousePressed() {
  noLoop();
}

void mouseReleased() {
  loop();
}
</code>
</example>

<description>
Stops Processing from continuously executing the code within <b>draw()</b>. If <b>loop()</b> is called, the code in <b>draw()</b> is executed continuously.
</description>

<syntax>
noLoop()
redraw()
draw()
</syntax>

<parameter>
<label></label>
<description></description>
</parameter>

<returns>None</returns>

<related>
loop()
</related>

<availability>1.0</availability>

<type>Function</type>

<partof>PDE</partof>

</root>
