<?xml version="1.0" encoding="UTF-8" standalone="yes"?>
<root>

<name>disconnect()</name>

<category>Server</category>

<subcategory>Server</subcategory>

<usage>Application</usage>

<example>
<image></image>
<code>
// Example by Tom Igoe

import processing.net.*;

int port = 10002;
Server myServer;

void setup()
{
  size(400, 400);
  background(0);
  myServer = new Server(this, port);
}

void draw()
{
  // Get the next available client
  Client thisClient = myServer.available();
  // If the client is not null, and says something, display what it said:
  if (thisClient !=null) {
    String whatClientSaid = thisClient.readString();
    // If the client says "exit", disconnect it
    if (whatClientSaid.equals("exit\r\n")) {
      thisClient.write("You will be disconnected now.\r\n");
      println(thisClient.ip() + "\t has been disconnected");
      myServer.disconnect(thisClient);
    } 
  } 
}

</code>
</example>

<description>
Disconnect a particular client.
</description>

<syntax>
<c>server</c>.disconnect(<b>client</b>)
</syntax>

<parameter>
<label>server</label>
<description>any variable of type Server</description>
</parameter>

<parameter>
<label>client</label>
<description>Client: the client to disconnect</description>
</parameter>

<returns>None</returns>

<related></related>

<availability>1.0</availability>

<type>Method</type>

<partof>Library</partof>


</root>
