<?xml version="1.0" encoding="UTF-8" standalone="yes"?>
<root>

<name>available()</name>

<category>Capture</category>

<subcategory></subcategory>

<usage>Web &amp; Application</usage>

<example>
<image></image>
<code>
import processing.video.*; 
Capture myCapture; 
 
void setup() { 
  size(200, 200); 
  String s = "Logitech QuickCam Messenger-WDM"; 
  myCapture = new Capture(this, s, width, height, 30);
} 
 
void draw() { 
  // myCapture.available() returns true 
  // when there is a new frame
  if(myCapture.available()) { 
    myCapture.read(); 
  } 
  image(myCapture, 0, 0); 
} 
 
</code>
</example>

<description>
Returns "true" when a new video frame is available to read.
</description>

<syntax>
<c>vid</c>.read()
</syntax>

<parameter>
<label>mov</label>
<description>any variable of type Capture</description>
</parameter>

<returns></returns>

<related></related>

<availability>1.0</availability>

<type>Method</type>

<partof>Library</partof>


</root>
