<?xml version="1.0" encoding="UTF-8" standalone="yes"?>
<root>

<name>GET()</name>

<category>
</category>

<subcategory>
</subcategory>

<description>
The GET method is used to fetch data from a web server.  It is the method
used by web browsers most commonly used to fetch the contents of a URL.  It
can also be used to execute scripts that return data based on parameters
passed in the URL string.
</description>

<syntax>
GET(<c>file</c>);
GET(<c>file</c>, <c>params</c>, <c>values</c>);
</syntax>

<parameter>
  <label>file</label>
  <description>String: name of file to fetch or script to execute on the web server</description>
</parameter>

<parameter>
  <label>params</label>
  <description>String[]: an array of String objects representing the names of parameters being passed to a script</description>
</parameter>

<parameter>
  <label>values</label>
  <description>String[]: an array of String objects representing the values of parameters being passed to a script</description>
</parameter>

<returns>
PRequest
</returns>

<related>
</related>

</root>
